[{"ID":0,"faithfulness":0.8411685973,"informativeness_step":0.7431374108,"informativeness_chain":0.872110866,"faithfulness_ww":0.9452499407,"repetition_word":0.0411397318,"repetition_step":0.0906513035,"discourse_representation":0.5548679829,"coherence_step_vs_step":0.9987800526,"perplexity_step":0.0189303094,"perplexity_chain":0.0404258516,"perplexity_step_max":0.0147587801,"grammar_step":0.9483057261,"grammar_step_max":0.907592535},{"ID":1,"faithfulness":0.7837523259,"informativeness_step":0.783195798,"informativeness_chain":0.9121743441,"faithfulness_ww":0.9450223133,"repetition_word":0.0508526699,"repetition_step":0.0727418363,"discourse_representation":0.9729475696,"coherence_step_vs_step":0.9573816024,"perplexity_step":0.0369785062,"perplexity_chain":0.0939827475,"perplexity_step_max":0.0316534605,"grammar_step":0.9138102233,"grammar_step_max":0.6990807056},{"ID":2,"faithfulness":0.7796103358,"informativeness_step":0.7796103358,"informativeness_chain":0.8898051977,"faithfulness_ww":0.9039448658,"repetition_word":1.0,"repetition_step":1.0,"discourse_representation":0.7748064697,"coherence_step_vs_step":0.9985135691,"perplexity_step":0.0653247681,"perplexity_chain":0.0653247681,"perplexity_step_max":0.0653247681,"grammar_step":0.7667289376,"grammar_step_max":0.7667289376},{"ID":3,"faithfulness":0.8654507995,"informativeness_step":0.8654507995,"informativeness_chain":0.932725355,"faithfulness_ww":0.9662124549,"repetition_word":1.0,"repetition_step":1.0,"discourse_representation":0.9419093877,"coherence_step_vs_step":0.9994319355,"perplexity_step":0.0640604937,"perplexity_chain":0.0640604937,"perplexity_step_max":0.0640604937,"grammar_step":0.9947013855,"grammar_step_max":0.9947013855},{"ID":4,"faithfulness":0.762703528,"informativeness_step":0.7709775517,"informativeness_chain":0.9353248626,"faithfulness_ww":0.9503694407,"repetition_word":0.0344176136,"repetition_step":0.067412287,"discourse_representation":0.9959531622,"coherence_step_vs_step":0.9973397593,"perplexity_step":0.0127710691,"perplexity_chain":0.0588255358,"perplexity_step_max":0.0057701459,"grammar_step":0.9589424531,"grammar_step_max":0.9208188057},{"ID":5,"faithfulness":0.7922947437,"informativeness_step":0.8235368644,"informativeness_chain":0.948259607,"faithfulness_ww":0.9554344494,"repetition_word":0.042126445,"repetition_step":0.1121170223,"discourse_representation":0.9747782703,"coherence_step_vs_step":0.9932624931,"perplexity_step":0.0143462007,"perplexity_chain":0.037913092,"perplexity_step_max":0.0067835665,"grammar_step":0.986021781,"grammar_step_max":0.9695334435},{"ID":6,"faithfulness":0.8297539234,"informativeness_step":0.8333585426,"informativeness_chain":0.9699582756,"faithfulness_ww":0.9524063769,"repetition_word":0.029967616,"repetition_step":0.0877598971,"discourse_representation":0.0512874126,"coherence_step_vs_step":0.0299078226,"perplexity_step":0.013978808,"perplexity_chain":0.059247218,"perplexity_step_max":0.0067539534,"grammar_step":0.9900655746,"grammar_step_max":0.9825147986},{"ID":7,"faithfulness":0.6777907833,"informativeness_step":0.7053209729,"informativeness_chain":0.8746566176,"faithfulness_ww":0.9218928258,"repetition_word":0.0526457237,"repetition_step":0.1832127571,"discourse_representation":0.123406589,"coherence_step_vs_step":0.9929908798,"perplexity_step":0.0160612838,"perplexity_chain":0.0475375401,"perplexity_step_max":0.0051482974,"grammar_step":0.9755019347,"grammar_step_max":0.945302844},{"ID":8,"faithfulness":0.8119125485,"informativeness_step":0.789386438,"informativeness_chain":0.9404320568,"faithfulness_ww":0.9476057067,"repetition_word":0.0383354336,"repetition_step":0.0427539796,"discourse_representation":0.8183967173,"coherence_step_vs_step":0.9968247858,"perplexity_step":0.0242400528,"perplexity_chain":0.091289811,"perplexity_step_max":0.0109591996,"grammar_step":0.9327305555,"grammar_step_max":0.7726384997},{"ID":9,"faithfulness":0.8309110701,"informativeness_step":0.8249924431,"informativeness_chain":0.9434603155,"faithfulness_ww":0.9368751731,"repetition_word":0.0442138956,"repetition_step":0.0753984302,"discourse_representation":0.9770754408,"coherence_step_vs_step":0.9972684986,"perplexity_step":0.0183749425,"perplexity_chain":0.0589892257,"perplexity_step_max":0.0073584304,"grammar_step":0.9910121411,"grammar_step_max":0.9822268486},{"ID":10,"faithfulness":0.7561956878,"informativeness_step":0.7282736654,"informativeness_chain":0.9093191475,"faithfulness_ww":0.9464132632,"repetition_word":0.0364426449,"repetition_step":0.0866589993,"discourse_representation":0.002813518,"coherence_step_vs_step":0.0076048374,"perplexity_step":0.0152030747,"perplexity_chain":0.0627854853,"perplexity_step_max":0.0023378989,"grammar_step":0.8995028734,"grammar_step_max":0.6449508667},{"ID":11,"faithfulness":0.7671622038,"informativeness_step":0.7499981038,"informativeness_chain":0.9245741218,"faithfulness_ww":0.9369191064,"repetition_word":1.0,"repetition_step":1.0,"discourse_representation":0.9887389643,"coherence_step_vs_step":0.9990538103,"perplexity_step":0.0020166887,"perplexity_chain":0.0020166887,"perplexity_step_max":0.0020166887,"grammar_step":0.9891824126,"grammar_step_max":0.9891824126},{"ID":12,"faithfulness":0.8355205774,"informativeness_step":0.7870949022,"informativeness_chain":0.9462268949,"faithfulness_ww":0.9519729297,"repetition_word":0.0417741239,"repetition_step":0.0606354028,"discourse_representation":0.0495174527,"coherence_step_vs_step":0.9620093442,"perplexity_step":0.0192527905,"perplexity_chain":0.072215909,"perplexity_step_max":0.0070078198,"grammar_step":0.9231356502,"grammar_step_max":0.7864262462},{"ID":13,"faithfulness":0.8361916244,"informativeness_step":0.8190744035,"informativeness_chain":0.9332636148,"faithfulness_ww":0.9461182573,"repetition_word":0.0409446508,"repetition_step":0.047045067,"discourse_representation":0.9938236149,"coherence_step_vs_step":0.9726596382,"perplexity_step":0.0180156339,"perplexity_chain":0.0771645946,"perplexity_step_max":0.011646426,"grammar_step":0.9922854751,"grammar_step_max":0.9888758063},{"ID":14,"faithfulness":0.8635570109,"informativeness_step":0.8362624432,"informativeness_chain":0.9689278752,"faithfulness_ww":0.9605860256,"repetition_word":0.0514868924,"repetition_step":0.1172052175,"discourse_representation":0.6128816307,"coherence_step_vs_step":0.9978075724,"perplexity_step":0.0043497376,"perplexity_chain":0.0117304235,"perplexity_step_max":0.0023161087,"grammar_step":0.758223633,"grammar_step_max":0.4626345038},{"ID":15,"faithfulness":0.833422929,"informativeness_step":0.8032833206,"informativeness_chain":0.9606646001,"faithfulness_ww":0.9679848744,"repetition_word":0.0418189093,"repetition_step":0.115216434,"discourse_representation":0.9312677085,"coherence_step_vs_step":0.9896809617,"perplexity_step":0.0127068386,"perplexity_chain":0.0484201868,"perplexity_step_max":0.0022029328,"grammar_step":0.979863435,"grammar_step_max":0.9698827267},{"ID":16,"faithfulness":0.769333031,"informativeness_step":0.7458156087,"informativeness_chain":0.9073873013,"faithfulness_ww":0.9580456101,"repetition_word":0.0472059716,"repetition_step":0.0853275061,"discourse_representation":0.0389762521,"coherence_step_vs_step":0.8404864222,"perplexity_step":0.0134122305,"perplexity_chain":0.0422181292,"perplexity_step_max":0.0086377418,"grammar_step":0.9465661645,"grammar_step_max":0.839655757},{"ID":17,"faithfulness":0.7951736674,"informativeness_step":0.7832867242,"informativeness_chain":0.9395475984,"faithfulness_ww":0.9527893036,"repetition_word":0.0375155608,"repetition_step":0.0837213546,"discourse_representation":0.9830245618,"coherence_step_vs_step":0.0409275293,"perplexity_step":0.0121213235,"perplexity_chain":0.0363760589,"perplexity_step_max":0.0066840265,"grammar_step":0.9796522856,"grammar_step_max":0.9653270245},{"ID":18,"faithfulness":0.7361669379,"informativeness_step":0.7187971276,"informativeness_chain":0.8515428677,"faithfulness_ww":0.9541350332,"repetition_word":0.0435987567,"repetition_step":0.055315733,"discourse_representation":0.0295983553,"coherence_step_vs_step":0.0358667374,"perplexity_step":0.0170120517,"perplexity_chain":0.0754333858,"perplexity_step_max":0.008706846,"grammar_step":0.9277653694,"grammar_step_max":0.7449305058},{"ID":19,"faithfulness":0.7323586494,"informativeness_step":0.6924763144,"informativeness_chain":0.870823659,"faithfulness_ww":0.9432569559,"repetition_word":1.0,"repetition_step":1.0,"discourse_representation":0.8653391451,"coherence_step_vs_step":0.9987428064,"perplexity_step":0.0053694141,"perplexity_chain":0.0053694141,"perplexity_step_max":0.0053694141,"grammar_step":0.9668836594,"grammar_step_max":0.9668836594},{"ID":20,"faithfulness":0.807646364,"informativeness_step":0.8076598644,"informativeness_chain":0.9319350272,"faithfulness_ww":0.937539474,"repetition_word":0.0590682672,"repetition_step":0.1594303548,"discourse_representation":0.7867757231,"coherence_step_vs_step":0.984408061,"perplexity_step":0.0269642343,"perplexity_chain":0.0424710671,"perplexity_step_max":0.0116158334,"grammar_step":0.9873176217,"grammar_step_max":0.981944561},{"ID":21,"faithfulness":0.6008813512,"informativeness_step":0.638898964,"informativeness_chain":0.797056146,"faithfulness_ww":0.9060439661,"repetition_word":0.0543400576,"repetition_step":0.1697474122,"discourse_representation":0.1019994617,"coherence_step_vs_step":0.9713653922,"perplexity_step":0.0041632745,"perplexity_chain":0.0118091465,"perplexity_step_max":0.0011699995,"grammar_step":0.7191300914,"grammar_step_max":0.3008894026},{"ID":22,"faithfulness":0.7959066033,"informativeness_step":0.8118173648,"informativeness_chain":0.9263886958,"faithfulness_ww":0.9353023431,"repetition_word":0.0605121553,"repetition_step":0.1504932866,"discourse_representation":0.9862773549,"coherence_step_vs_step":0.9956269288,"perplexity_step":0.0308656859,"perplexity_chain":0.0560568512,"perplexity_step_max":0.0162094417,"grammar_step":0.9826227228,"grammar_step_max":0.9689388275},{"ID":23,"faithfulness":0.7979005799,"informativeness_step":0.7961209255,"informativeness_chain":0.9208068401,"faithfulness_ww":0.9546138399,"repetition_word":0.0432788378,"repetition_step":0.0817650408,"discourse_representation":0.9585844614,"coherence_step_vs_step":0.9954505567,"perplexity_step":0.0070640465,"perplexity_chain":0.0262152388,"perplexity_step_max":0.0041747686,"grammar_step":0.755981531,"grammar_step_max":0.0970330089},{"ID":24,"faithfulness":0.8456794421,"informativeness_step":0.8533670952,"informativeness_chain":0.9583529979,"faithfulness_ww":0.9572707569,"repetition_word":0.0481178047,"repetition_step":0.1105953902,"discourse_representation":0.1159439683,"coherence_step_vs_step":0.0027522445,"perplexity_step":0.022536968,"perplexity_chain":0.0476897814,"perplexity_step_max":0.0098902375,"grammar_step":0.9767064452,"grammar_step_max":0.9661497474},{"ID":25,"faithfulness":0.792729795,"informativeness_step":0.792729795,"informativeness_chain":0.9064187109,"faithfulness_ww":0.9513230551,"repetition_word":0.0609731227,"repetition_step":0.2591397213,"discourse_representation":0.9770025648,"coherence_step_vs_step":0.9859688291,"perplexity_step":0.0203109197,"perplexity_chain":0.0255959447,"perplexity_step_max":0.0193088182,"grammar_step":0.988024503,"grammar_step_max":0.9859434366},{"ID":26,"faithfulness":0.7735842566,"informativeness_step":0.8020452112,"informativeness_chain":0.9488412887,"faithfulness_ww":0.9504640112,"repetition_word":0.0533878282,"repetition_step":0.0924591571,"discourse_representation":0.9181448817,"coherence_step_vs_step":0.9958579037,"perplexity_step":0.029068835,"perplexity_chain":0.0471347405,"perplexity_step_max":0.0184977381,"grammar_step":0.9749986331,"grammar_step_max":0.9677366018},{"ID":27,"faithfulness":0.8547300994,"informativeness_step":0.8197276622,"informativeness_chain":0.9414555281,"faithfulness_ww":0.9556554087,"repetition_word":0.0304746393,"repetition_step":0.0292334557,"discourse_representation":0.1422937512,"coherence_step_vs_step":0.1102499366,"perplexity_step":0.0279620754,"perplexity_chain":0.0819795223,"perplexity_step_max":0.0175912396,"grammar_step":0.9068852067,"grammar_step_max":0.7743133903},{"ID":28,"faithfulness":0.8161245783,"informativeness_step":0.8177342253,"informativeness_chain":0.9385341108,"faithfulness_ww":0.9511726476,"repetition_word":0.0439438943,"repetition_step":0.1826377437,"discourse_representation":0.6216466129,"coherence_step_vs_step":0.9971709999,"perplexity_step":0.0315210498,"perplexity_chain":0.0642986016,"perplexity_step_max":0.0212581719,"grammar_step":0.9811203678,"grammar_step_max":0.9608966112},{"ID":29,"faithfulness":0.8641326874,"informativeness_step":0.8174170714,"informativeness_chain":0.8589192331,"faithfulness_ww":0.9566369875,"repetition_word":0.0162368715,"repetition_step":0.0683388263,"discourse_representation":0.002974093,"coherence_step_vs_step":0.8040846884,"perplexity_step":0.0064680014,"perplexity_chain":0.0600326077,"perplexity_step_max":0.0030163089,"grammar_step":0.9179489762,"grammar_step_max":0.8413658738},{"ID":30,"faithfulness":0.8010392785,"informativeness_step":0.717219741,"informativeness_chain":0.8159227148,"faithfulness_ww":0.9413158827,"repetition_word":1.0,"repetition_step":1.0,"discourse_representation":0.0034211278,"coherence_step_vs_step":0.9977604821,"perplexity_step":0.0122528104,"perplexity_chain":0.0122528104,"perplexity_step_max":0.0122528104,"grammar_step":0.8067685962,"grammar_step_max":0.8067685962},{"ID":31,"faithfulness":0.801960811,"informativeness_step":0.7215759823,"informativeness_chain":0.8111712635,"faithfulness_ww":0.9443566407,"repetition_word":0.1022695577,"repetition_step":0.106516704,"discourse_representation":0.5311529636,"coherence_step_vs_step":0.9932438778,"perplexity_step":0.0249943383,"perplexity_chain":0.0433054401,"perplexity_step_max":0.0150369735,"grammar_step":0.872895062,"grammar_step_max":0.7912675142},{"ID":32,"faithfulness":0.8719507933,"informativeness_step":0.8366435442,"informativeness_chain":0.8948962986,"faithfulness_ww":0.964597447,"repetition_word":0.0184577809,"repetition_step":0.0582376122,"discourse_representation":0.022051692,"coherence_step_vs_step":0.0046854019,"perplexity_step":0.0052644932,"perplexity_chain":0.0719218471,"perplexity_step_max":0.0035647086,"grammar_step":0.840054369,"grammar_step_max":0.7021852136},{"ID":33,"faithfulness":0.756076213,"informativeness_step":0.7974401694,"informativeness_chain":0.9032127857,"faithfulness_ww":0.9098945514,"repetition_word":0.0487167062,"repetition_step":0.0617516637,"discourse_representation":0.9878617777,"coherence_step_vs_step":0.0250997543,"perplexity_step":0.0209718325,"perplexity_chain":0.0302570407,"perplexity_step_max":0.0169361924,"grammar_step":0.9143810421,"grammar_step_max":0.7539622188},{"ID":34,"faithfulness":0.864583239,"informativeness_step":0.7725999001,"informativeness_chain":0.8233951703,"faithfulness_ww":0.9576078594,"repetition_word":0.0427552966,"repetition_step":0.0765115321,"discourse_representation":0.1272243857,"coherence_step_vs_step":0.937221989,"perplexity_step":0.008489126,"perplexity_chain":0.0443963281,"perplexity_step_max":0.0056419124,"grammar_step":0.9880748838,"grammar_step_max":0.974098146},{"ID":35,"faithfulness":0.9216223657,"informativeness_step":0.8446435848,"informativeness_chain":0.9642782956,"faithfulness_ww":0.9810076199,"repetition_word":1.0,"repetition_step":1.0,"discourse_representation":0.0011270642,"coherence_step_vs_step":0.998057397,"perplexity_step":0.0554639305,"perplexity_chain":0.0554639305,"perplexity_step_max":0.0554639305,"grammar_step":0.9920557141,"grammar_step_max":0.9920557141},{"ID":36,"faithfulness":0.7646936874,"informativeness_step":0.7260323449,"informativeness_chain":0.8352797851,"faithfulness_ww":0.9358218424,"repetition_word":0.0507077674,"repetition_step":0.0871470869,"discourse_representation":0.2913120985,"coherence_step_vs_step":0.9901622217,"perplexity_step":0.0111571219,"perplexity_chain":0.0466211153,"perplexity_step_max":0.0051799545,"grammar_step":0.8153159221,"grammar_step_max":0.4836804271},{"ID":37,"faithfulness":0.6515119523,"informativeness_step":0.6515119523,"informativeness_chain":0.8257559761,"faithfulness_ww":0.9247953861,"repetition_word":1.0,"repetition_step":1.0,"discourse_representation":0.9979747341,"coherence_step_vs_step":0.9994013421,"perplexity_step":0.0312365245,"perplexity_chain":0.0312365245,"perplexity_step_max":0.0312365245,"grammar_step":0.9925765395,"grammar_step_max":0.9925765395},{"ID":38,"faithfulness":0.7220489085,"informativeness_step":0.7542413883,"informativeness_chain":0.8665498495,"faithfulness_ww":0.9206394121,"repetition_word":0.0454768656,"repetition_step":0.1209950894,"discourse_representation":0.1481970549,"coherence_step_vs_step":0.9260920882,"perplexity_step":0.0211496018,"perplexity_chain":0.0786369057,"perplexity_step_max":0.004344798,"grammar_step":0.8742347211,"grammar_step_max":0.7652100325},{"ID":39,"faithfulness":0.7376912385,"informativeness_step":0.7376912385,"informativeness_chain":0.8688456267,"faithfulness_ww":0.9255878207,"repetition_word":1.0,"repetition_step":1.0,"discourse_representation":0.996947136,"coherence_step_vs_step":0.9994649112,"perplexity_step":0.007986221,"perplexity_chain":0.007986221,"perplexity_step_max":0.007986221,"grammar_step":0.1213220358,"grammar_step_max":0.1213220358},{"ID":40,"faithfulness":0.7076001813,"informativeness_step":0.6994817654,"informativeness_chain":0.8705852032,"faithfulness_ww":0.9276149483,"repetition_word":0.0685192154,"repetition_step":0.0660909563,"discourse_representation":0.6261524856,"coherence_step_vs_step":0.0085622668,"perplexity_step":0.0269074761,"perplexity_chain":0.1267182422,"perplexity_step_max":0.0045446674,"grammar_step":0.8993102908,"grammar_step_max":0.7902984023},{"ID":41,"faithfulness":0.7183825225,"informativeness_step":0.6885587052,"informativeness_chain":0.895691663,"faithfulness_ww":0.927007549,"repetition_word":0.1103214448,"repetition_step":0.1921701729,"discourse_representation":0.9570436031,"coherence_step_vs_step":0.9707230497,"perplexity_step":0.0238556708,"perplexity_chain":0.0333731315,"perplexity_step_max":0.0147932197,"grammar_step":0.9194522202,"grammar_step_max":0.8950130939},{"ID":42,"faithfulness":0.7103810906,"informativeness_step":0.7103810906,"informativeness_chain":0.8551905453,"faithfulness_ww":0.9325592304,"repetition_word":1.0,"repetition_step":1.0,"discourse_representation":0.9870756557,"coherence_step_vs_step":0.9953270461,"perplexity_step":0.0224700269,"perplexity_chain":0.0224700269,"perplexity_step_max":0.0224700269,"grammar_step":0.9352499247,"grammar_step_max":0.9352499247},{"ID":43,"faithfulness":0.8100726008,"informativeness_step":0.7557177991,"informativeness_chain":0.8792097121,"faithfulness_ww":0.929729458,"repetition_word":0.1082359414,"repetition_step":0.1443984807,"discourse_representation":0.9046619534,"coherence_step_vs_step":0.9833389428,"perplexity_step":0.029337015,"perplexity_chain":0.0461404377,"perplexity_step_max":0.0142421794,"grammar_step":0.9286249578,"grammar_step_max":0.8756143451},{"ID":44,"faithfulness":0.8115973473,"informativeness_step":0.8115973473,"informativeness_chain":0.9057986736,"faithfulness_ww":0.9426049334,"repetition_word":1.0,"repetition_step":1.0,"discourse_representation":0.9990256572,"coherence_step_vs_step":0.9913278557,"perplexity_step":0.0529989935,"perplexity_chain":0.0529989935,"perplexity_step_max":0.0529989935,"grammar_step":0.8009648323,"grammar_step_max":0.8009648323},{"ID":45,"faithfulness":0.7299348265,"informativeness_step":0.7777274325,"informativeness_chain":0.893168807,"faithfulness_ww":0.9325120657,"repetition_word":0.0899247091,"repetition_step":0.1457455605,"discourse_representation":0.9976145211,"coherence_step_vs_step":0.1074902415,"perplexity_step":0.0424703451,"perplexity_chain":0.0614989076,"perplexity_step_max":0.0313133341,"grammar_step":0.9021691382,"grammar_step_max":0.8362060785},{"ID":46,"faithfulness":0.8157352209,"informativeness_step":0.7827101586,"informativeness_chain":0.8707463816,"faithfulness_ww":0.95163078,"repetition_word":0.0661553878,"repetition_step":0.1753346771,"discourse_representation":0.9708058052,"coherence_step_vs_step":0.981711857,"perplexity_step":0.015833494,"perplexity_chain":0.0295600272,"perplexity_step_max":0.010836651,"grammar_step":0.8959546089,"grammar_step_max":0.7955926657},{"ID":47,"faithfulness":0.8266167343,"informativeness_step":0.7962252125,"informativeness_chain":0.9306850284,"faithfulness_ww":0.9442131414,"repetition_word":1.0,"repetition_step":1.0,"discourse_representation":0.9867035523,"coherence_step_vs_step":0.9957105285,"perplexity_step":0.0119613804,"perplexity_chain":0.0119613804,"perplexity_step_max":0.0119613804,"grammar_step":0.9815425277,"grammar_step_max":0.9815425277},{"ID":48,"faithfulness":0.899017781,"informativeness_step":0.8140956266,"informativeness_chain":0.9060693383,"faithfulness_ww":0.9640042096,"repetition_word":1.0,"repetition_step":1.0,"discourse_representation":0.9957656739,"coherence_step_vs_step":0.9973353804,"perplexity_step":0.0067898576,"perplexity_chain":0.0067898576,"perplexity_step_max":0.0067898576,"grammar_step":0.9730023146,"grammar_step_max":0.9730023146},{"ID":49,"faithfulness":0.8175756882,"informativeness_step":0.7787063991,"informativeness_chain":0.9061680436,"faithfulness_ww":0.9484591291,"repetition_word":0.0514846005,"repetition_step":0.0796854496,"discourse_representation":0.944639504,"coherence_step_vs_step":0.9835691303,"perplexity_step":0.0036536137,"perplexity_chain":0.0210354026,"perplexity_step_max":0.0016011232,"grammar_step":0.6291946868,"grammar_step_max":0.3417538106},{"ID":50,"faithfulness":0.799879089,"informativeness_step":0.79235816,"informativeness_chain":0.9564036429,"faithfulness_ww":0.9348613614,"repetition_word":0.0527050462,"repetition_step":0.0608879924,"discourse_representation":0.0623809099,"coherence_step_vs_step":0.79692927,"perplexity_step":0.0000034351,"perplexity_chain":0.0105559919,"perplexity_step_max":0.0000001375,"grammar_step":0.4431731602,"grammar_step_max":0.2054510415},{"ID":51,"faithfulness":0.7575056851,"informativeness_step":0.7575056851,"informativeness_chain":0.8671005145,"faithfulness_ww":0.9192200005,"repetition_word":0.0680947463,"repetition_step":0.1626776829,"discourse_representation":0.8506037146,"coherence_step_vs_step":0.9838451594,"perplexity_step":0.0037936843,"perplexity_chain":0.0085432175,"perplexity_step_max":0.0020978926,"grammar_step":0.5602073371,"grammar_step_max":0.1330841184},{"ID":52,"faithfulness":0.8039231002,"informativeness_step":0.8039231002,"informativeness_chain":0.9019615203,"faithfulness_ww":0.9238260699,"repetition_word":1.0,"repetition_step":1.0,"discourse_representation":0.9971583476,"coherence_step_vs_step":0.9995015753,"perplexity_step":0.006680856,"perplexity_chain":0.006680856,"perplexity_step_max":0.006680856,"grammar_step":0.9833757281,"grammar_step_max":0.9833757281},{"ID":53,"faithfulness":0.8504890203,"informativeness_step":0.7586072451,"informativeness_chain":0.909713313,"faithfulness_ww":0.9554155263,"repetition_word":0.0353033211,"repetition_step":0.0805883706,"discourse_representation":0.9987914785,"coherence_step_vs_step":0.998522038,"perplexity_step":0.0088460085,"perplexity_chain":0.0295983278,"perplexity_step_max":0.0080832542,"grammar_step":0.9606181383,"grammar_step_max":0.9326756597},{"ID":54,"faithfulness":0.8243309657,"informativeness_step":0.7943858157,"informativeness_chain":0.9042159319,"faithfulness_ww":0.9428058806,"repetition_word":0.0471199729,"repetition_step":0.0629319698,"discourse_representation":0.9988478344,"coherence_step_vs_step":0.9888344239,"perplexity_step":0.0259148633,"perplexity_chain":0.0596884712,"perplexity_step_max":0.0190951054,"grammar_step":0.9893718958,"grammar_step_max":0.9851613045},{"ID":55,"faithfulness":0.8424922576,"informativeness_step":0.8139894433,"informativeness_chain":0.8988696784,"faithfulness_ww":0.9630244175,"repetition_word":0.0196568565,"repetition_step":0.0535595715,"discourse_representation":0.0008144975,"coherence_step_vs_step":0.0174520612,"perplexity_step":0.0022030798,"perplexity_chain":0.0582380742,"perplexity_step_max":0.0002472039,"grammar_step":0.9392345349,"grammar_step_max":0.8990971446},{"ID":56,"faithfulness":0.846441552,"informativeness_step":0.7653443864,"informativeness_chain":0.8636744395,"faithfulness_ww":0.956274865,"repetition_word":0.0499859475,"repetition_step":0.2096048109,"discourse_representation":0.0798599124,"coherence_step_vs_step":0.9994710635,"perplexity_step":0.0104550578,"perplexity_chain":0.0194578652,"perplexity_step_max":0.0045163415,"grammar_step":0.6802297831,"grammar_step_max":0.3719980717},{"ID":57,"faithfulness":0.8817240596,"informativeness_step":0.7869361921,"informativeness_chain":0.8796184659,"faithfulness_ww":0.9559345333,"repetition_word":1.0,"repetition_step":1.0,"discourse_representation":0.0018526316,"coherence_step_vs_step":0.9985543049,"perplexity_step":0.004656285,"perplexity_chain":0.004656285,"perplexity_step_max":0.004656285,"grammar_step":0.4038338065,"grammar_step_max":0.4038338065},{"ID":58,"faithfulness":0.7762460485,"informativeness_step":0.6955067158,"informativeness_chain":0.8360781223,"faithfulness_ww":0.9338711793,"repetition_word":0.0338752705,"repetition_step":0.1490359455,"discourse_representation":0.9446311966,"coherence_step_vs_step":0.4480698705,"perplexity_step":0.0084838583,"perplexity_chain":0.0261520817,"perplexity_step_max":0.0056354675,"grammar_step":0.7572744489,"grammar_step_max":0.5188223124},{"ID":59,"faithfulness":0.8765038252,"informativeness_step":0.7780192941,"informativeness_chain":0.8405644596,"faithfulness_ww":0.9456344979,"repetition_word":0.0386895128,"repetition_step":0.0348988026,"discourse_representation":0.1490057111,"coherence_step_vs_step":0.9979512158,"perplexity_step":0.0173702249,"perplexity_chain":0.0701121753,"perplexity_step_max":0.0055938841,"grammar_step":0.9321264327,"grammar_step_max":0.8833591342},{"ID":60,"faithfulness":0.7394593731,"informativeness_step":0.7503119968,"informativeness_chain":0.9321077764,"faithfulness_ww":0.9448018384,"repetition_word":0.051728509,"repetition_step":0.1291045099,"discourse_representation":0.8500045389,"coherence_step_vs_step":0.9926830204,"perplexity_step":0.0143184481,"perplexity_chain":0.0247692503,"perplexity_step_max":0.0077363301,"grammar_step":0.7311362624,"grammar_step_max":0.6353785992},{"ID":61,"faithfulness":0.8142071664,"informativeness_step":0.6945055061,"informativeness_chain":0.7649254967,"faithfulness_ww":0.9649302529,"repetition_word":1.0,"repetition_step":1.0,"discourse_representation":0.9939768598,"coherence_step_vs_step":0.9996627455,"perplexity_step":0.0227136637,"perplexity_chain":0.0227136637,"perplexity_step_max":0.0227136637,"grammar_step":0.9935693741,"grammar_step_max":0.9935693741},{"ID":62,"faithfulness":0.7628958225,"informativeness_step":0.6650662993,"informativeness_chain":0.7564893891,"faithfulness_ww":0.950612243,"repetition_word":1.0,"repetition_step":1.0,"discourse_representation":0.9647917114,"coherence_step_vs_step":0.9993302503,"perplexity_step":0.0219527279,"perplexity_chain":0.0219527279,"perplexity_step_max":0.0219527279,"grammar_step":0.9893677831,"grammar_step_max":0.9893677831},{"ID":63,"faithfulness":0.7871237695,"informativeness_step":0.7497546698,"informativeness_chain":0.8999656886,"faithfulness_ww":0.9408502259,"repetition_word":0.0650999142,"repetition_step":0.1265072078,"discourse_representation":0.9641867056,"coherence_step_vs_step":0.9877106752,"perplexity_step":0.0064483125,"perplexity_chain":0.0147533059,"perplexity_step_max":0.0026490298,"grammar_step":0.4982222691,"grammar_step_max":0.1818184406},{"ID":64,"faithfulness":0.8514728118,"informativeness_step":0.8570559449,"informativeness_chain":0.8989030421,"faithfulness_ww":0.9613953719,"repetition_word":0.0336770676,"repetition_step":0.0463740081,"discourse_representation":0.2120950818,"coherence_step_vs_step":0.2120930552,"perplexity_step":0.006424374,"perplexity_chain":0.0819470637,"perplexity_step_max":0.0012104501,"grammar_step":0.9121934995,"grammar_step_max":0.6535558701},{"ID":65,"faithfulness":0.8362573896,"informativeness_step":0.7687940227,"informativeness_chain":0.8410451263,"faithfulness_ww":0.96270622,"repetition_word":0.0233853405,"repetition_step":0.0537945777,"discourse_representation":0.2394912243,"coherence_step_vs_step":0.056882441,"perplexity_step":0.0204694627,"perplexity_chain":0.1139865061,"perplexity_step_max":0.0128296104,"grammar_step":0.8853636427,"grammar_step_max":0.2740077674},{"ID":66,"faithfulness":0.811896354,"informativeness_step":0.7777004483,"informativeness_chain":0.8437764049,"faithfulness_ww":0.9578260421,"repetition_word":0.0381506657,"repetition_step":0.1085026264,"discourse_representation":0.0023653507,"coherence_step_vs_step":0.9517415948,"perplexity_step":0.0149080108,"perplexity_chain":0.0466376689,"perplexity_step_max":0.0103557702,"grammar_step":0.9511436224,"grammar_step_max":0.9240531325},{"ID":67,"faithfulness":0.7898921371,"informativeness_step":0.7713321121,"informativeness_chain":0.8972922564,"faithfulness_ww":0.9560985028,"repetition_word":0.0489001686,"repetition_step":0.1491438299,"discourse_representation":0.0010047555,"coherence_step_vs_step":0.5244864523,"perplexity_step":0.0133727586,"perplexity_chain":0.0577003469,"perplexity_step_max":0.0062518746,"grammar_step":0.9382670124,"grammar_step_max":0.8500464559},{"ID":68,"faithfulness":0.8689846694,"informativeness_step":0.8002109472,"informativeness_chain":0.8740438968,"faithfulness_ww":0.9554344734,"repetition_word":0.0429343444,"repetition_step":0.059630245,"discourse_representation":0.9981751775,"coherence_step_vs_step":0.9984631484,"perplexity_step":0.0095338352,"perplexity_chain":0.0222061782,"perplexity_step_max":0.0078425386,"grammar_step":0.9613677263,"grammar_step_max":0.9351533651},{"ID":69,"faithfulness":0.7708795965,"informativeness_step":0.7244830259,"informativeness_chain":0.8539259955,"faithfulness_ww":0.9506240223,"repetition_word":0.0538037966,"repetition_step":0.1157244295,"discourse_representation":0.0012270808,"coherence_step_vs_step":0.0194399357,"perplexity_step":0.0054977355,"perplexity_chain":0.020389796,"perplexity_step_max":0.0013963301,"grammar_step":0.8243845999,"grammar_step_max":0.6145026088},{"ID":70,"faithfulness":0.7459755739,"informativeness_step":0.7562365308,"informativeness_chain":0.8880387396,"faithfulness_ww":0.9401527698,"repetition_word":0.0488418539,"repetition_step":0.1024590135,"discourse_representation":0.1736815572,"coherence_step_vs_step":0.7035312653,"perplexity_step":0.0180654977,"perplexity_chain":0.0485399565,"perplexity_step_max":0.0121626072,"grammar_step":0.9618327022,"grammar_step_max":0.9487546682},{"ID":71,"faithfulness":0.864892453,"informativeness_step":0.7695393725,"informativeness_chain":0.8883575946,"faithfulness_ww":0.9633083523,"repetition_word":1.0,"repetition_step":1.0,"discourse_representation":0.0923649669,"coherence_step_vs_step":0.998738298,"perplexity_step":0.0203820534,"perplexity_chain":0.0203820534,"perplexity_step_max":0.0203820534,"grammar_step":0.904854238,"grammar_step_max":0.904854238},{"ID":72,"faithfulness":0.850487262,"informativeness_step":0.7993486486,"informativeness_chain":0.9359408915,"faithfulness_ww":0.9505186531,"repetition_word":0.0474136861,"repetition_step":0.0736857802,"discourse_representation":0.9309014678,"coherence_step_vs_step":0.7655662149,"perplexity_step":0.0222612602,"perplexity_chain":0.0492450691,"perplexity_step_max":0.0181285755,"grammar_step":0.9861619174,"grammar_step_max":0.983797133},{"ID":73,"faithfulness":0.6796674952,"informativeness_step":0.6724864207,"informativeness_chain":0.8679849431,"faithfulness_ww":0.932379345,"repetition_word":0.0374356679,"repetition_step":0.0586146116,"discourse_representation":0.9193815216,"coherence_step_vs_step":0.9937669537,"perplexity_step":0.0130315376,"perplexity_chain":0.0429572183,"perplexity_step_max":0.0054554449,"grammar_step":0.9944888353,"grammar_step_max":0.9943212271},{"ID":74,"faithfulness":0.7304181705,"informativeness_step":0.6540544774,"informativeness_chain":0.8558012843,"faithfulness_ww":0.9466453182,"repetition_word":0.0388781617,"repetition_step":0.1156675816,"discourse_representation":0.0061058402,"coherence_step_vs_step":0.9916555285,"perplexity_step":0.0212901534,"perplexity_chain":0.0634308243,"perplexity_step_max":0.0105618374,"grammar_step":0.9834216038,"grammar_step_max":0.9774723649},{"ID":75,"faithfulness":0.8353924726,"informativeness_step":0.7604304704,"informativeness_chain":0.9195460081,"faithfulness_ww":0.9561593303,"repetition_word":0.0394786398,"repetition_step":0.1387200654,"discourse_representation":0.0017043948,"coherence_step_vs_step":0.0027031302,"perplexity_step":0.0081083339,"perplexity_chain":0.0310097009,"perplexity_step_max":0.002520992,"grammar_step":0.8468617251,"grammar_step_max":0.4886145294},{"ID":76,"faithfulness":0.7658627555,"informativeness_step":0.7523337808,"informativeness_chain":0.91217722,"faithfulness_ww":0.9411528968,"repetition_word":0.0433470137,"repetition_step":0.1177459359,"discourse_representation":0.3411231041,"coherence_step_vs_step":0.4418625832,"perplexity_step":0.0152237993,"perplexity_chain":0.0477464952,"perplexity_step_max":0.0027315439,"grammar_step":0.9850266278,"grammar_step_max":0.9784268141},{"ID":77,"faithfulness":0.7855936587,"informativeness_step":0.7099846685,"informativeness_chain":0.8497554809,"faithfulness_ww":0.9511307737,"repetition_word":0.0313687391,"repetition_step":0.0325631499,"discourse_representation":0.0016699433,"coherence_step_vs_step":0.2837813497,"perplexity_step":0.0078525558,"perplexity_chain":0.0986386793,"perplexity_step_max":0.0004241252,"grammar_step":0.8939408915,"grammar_step_max":0.6357044578},{"ID":78,"faithfulness":0.7676219543,"informativeness_step":0.7223092543,"informativeness_chain":0.9411348999,"faithfulness_ww":0.9533680411,"repetition_word":0.0587057567,"repetition_step":0.1158821583,"discourse_representation":0.0018841028,"coherence_step_vs_step":0.987122546,"perplexity_step":0.0169868119,"perplexity_chain":0.0306281125,"perplexity_step_max":0.0127978808,"grammar_step":0.9827552636,"grammar_step_max":0.9738361239},{"ID":79,"faithfulness":0.7727120941,"informativeness_step":0.7345534918,"informativeness_chain":0.9136240482,"faithfulness_ww":0.9483316363,"repetition_word":0.0402127683,"repetition_step":0.1165628284,"discourse_representation":0.0562460423,"coherence_step_vs_step":0.7106521726,"perplexity_step":0.016804236,"perplexity_chain":0.0492128743,"perplexity_step_max":0.0054681074,"grammar_step":0.9693163236,"grammar_step_max":0.9065172672},{"ID":80,"faithfulness":0.7958572805,"informativeness_step":0.7594964159,"informativeness_chain":0.8814577311,"faithfulness_ww":0.949669387,"repetition_word":0.0387073341,"repetition_step":0.0752522051,"discourse_representation":0.9824223109,"coherence_step_vs_step":0.9953799425,"perplexity_step":0.0223022336,"perplexity_chain":0.0761057015,"perplexity_step_max":0.0099111941,"grammar_step":0.9569780469,"grammar_step_max":0.8165718317},{"ID":81,"faithfulness":0.7932813317,"informativeness_step":0.7509578582,"informativeness_chain":0.9203275591,"faithfulness_ww":0.9555520687,"repetition_word":0.0328869315,"repetition_step":0.0997914374,"discourse_representation":0.0124936104,"coherence_step_vs_step":0.9930116031,"perplexity_step":0.0234738707,"perplexity_chain":0.0575987322,"perplexity_step_max":0.0234628048,"grammar_step":0.8968044221,"grammar_step_max":0.8042801619},{"ID":82,"faithfulness":0.8353933394,"informativeness_step":0.7487842128,"informativeness_chain":0.8942645043,"faithfulness_ww":0.9645517973,"repetition_word":0.0633126646,"repetition_step":0.1666485891,"discourse_representation":0.000923872,"coherence_step_vs_step":0.9745919947,"perplexity_step":0.0115708982,"perplexity_chain":0.0203692285,"perplexity_step_max":0.0108732248,"grammar_step":0.8417026401,"grammar_step_max":0.696408987},{"ID":83,"faithfulness":0.8157121092,"informativeness_step":0.7620962035,"informativeness_chain":0.937752068,"faithfulness_ww":0.9537348401,"repetition_word":0.0506579106,"repetition_step":0.085817039,"discourse_representation":0.0294578075,"coherence_step_vs_step":0.9966626358,"perplexity_step":0.0055454049,"perplexity_chain":0.0133911546,"perplexity_step_max":0.0031629854,"grammar_step":0.4829899073,"grammar_step_max":0.4118230939},{"ID":84,"faithfulness":0.9674684107,"informativeness_step":0.8486525428,"informativeness_chain":0.8937372714,"faithfulness_ww":0.9791121929,"repetition_word":1.0,"repetition_step":1.0,"discourse_representation":0.0010723472,"coherence_step_vs_step":0.9984884788,"perplexity_step":0.0353257463,"perplexity_chain":0.0353257463,"perplexity_step_max":0.0353257463,"grammar_step":0.7964084744,"grammar_step_max":0.7964084744},{"ID":85,"faithfulness":0.786425973,"informativeness_step":0.767929256,"informativeness_chain":0.9307564944,"faithfulness_ww":0.9540897686,"repetition_word":0.0456007075,"repetition_step":0.1092818975,"discourse_representation":0.0065103769,"coherence_step_vs_step":0.0372117162,"perplexity_step":0.0241310246,"perplexity_chain":0.0709433713,"perplexity_step_max":0.0100685017,"grammar_step":0.9550848802,"grammar_step_max":0.9071606398},{"ID":86,"faithfulness":0.8412989974,"informativeness_step":0.7313964147,"informativeness_chain":0.888602674,"faithfulness_ww":0.9590638033,"repetition_word":0.0468161494,"repetition_step":0.0822825283,"discourse_representation":0.0010077357,"coherence_step_vs_step":0.1687972546,"perplexity_step":0.0077463389,"perplexity_chain":0.0273812041,"perplexity_step_max":0.0041489777,"grammar_step":0.9213328063,"grammar_step_max":0.8580046892},{"ID":87,"faithfulness":0.9517517686,"informativeness_step":0.8819725513,"informativeness_chain":0.9354881048,"faithfulness_ww":0.9589505773,"repetition_word":1.0,"repetition_step":1.0,"discourse_representation":0.9250896946,"coherence_step_vs_step":0.9917874578,"perplexity_step":0.0338134909,"perplexity_chain":0.0338134909,"perplexity_step_max":0.0338134909,"grammar_step":0.2296408415,"grammar_step_max":0.2296408415},{"ID":88,"faithfulness":0.8305318058,"informativeness_step":0.8090556189,"informativeness_chain":0.9425964057,"faithfulness_ww":0.9523365578,"repetition_word":0.0453452031,"repetition_step":0.0990426242,"discourse_representation":0.2903521657,"coherence_step_vs_step":0.9897026075,"perplexity_step":0.0142637027,"perplexity_chain":0.0356993511,"perplexity_step_max":0.0104565934,"grammar_step":0.9663879275,"grammar_step_max":0.9469169974},{"ID":89,"faithfulness":0.7889797688,"informativeness_step":0.7661764631,"informativeness_chain":0.8968291283,"faithfulness_ww":0.9502332935,"repetition_word":0.0422962629,"repetition_step":0.0940526277,"discourse_representation":0.0146764517,"coherence_step_vs_step":0.9978247578,"perplexity_step":0.0140437448,"perplexity_chain":0.0494361941,"perplexity_step_max":0.0117062677,"grammar_step":0.94098562,"grammar_step_max":0.8511003256},{"ID":90,"faithfulness":0.7913264036,"informativeness_step":0.7845141105,"informativeness_chain":0.9118381292,"faithfulness_ww":0.9628137699,"repetition_word":0.0419704378,"repetition_step":0.131385386,"discourse_representation":0.4861687422,"coherence_step_vs_step":0.9835424051,"perplexity_step":0.0268962052,"perplexity_chain":0.0597176657,"perplexity_step_max":0.0251614147,"grammar_step":0.9781076014,"grammar_step_max":0.9773337245},{"ID":91,"faithfulness":0.8942225377,"informativeness_step":0.8880476639,"informativeness_chain":0.9716549069,"faithfulness_ww":0.9690062226,"repetition_word":0.0423659459,"repetition_step":0.0651725084,"discourse_representation":0.0060922503,"coherence_step_vs_step":0.9694156647,"perplexity_step":0.01389484,"perplexity_chain":0.071174287,"perplexity_step_max":0.0082315391,"grammar_step":0.9568690062,"grammar_step_max":0.9243798852},{"ID":92,"faithfulness":0.8243163563,"informativeness_step":0.7801389924,"informativeness_chain":0.8626303077,"faithfulness_ww":0.9436923725,"repetition_word":0.0284764171,"repetition_step":0.0265963972,"discourse_representation":0.2579862475,"coherence_step_vs_step":0.1661618948,"perplexity_step":0.0132275668,"perplexity_chain":0.0815874431,"perplexity_step_max":0.006383891,"grammar_step":0.8181945905,"grammar_step_max":0.459072262},{"ID":93,"faithfulness":0.8243163563,"informativeness_step":0.7801389924,"informativeness_chain":0.8626303077,"faithfulness_ww":0.9436923725,"repetition_word":0.0284764171,"repetition_step":0.0265963972,"discourse_representation":0.2579862475,"coherence_step_vs_step":0.1661618948,"perplexity_step":0.0132275668,"perplexity_chain":0.0815874431,"perplexity_step_max":0.006383891,"grammar_step":0.8181945905,"grammar_step_max":0.459072262},{"ID":94,"faithfulness":0.8912921151,"informativeness_step":0.788383377,"informativeness_chain":0.9067996889,"faithfulness_ww":0.9737436671,"repetition_word":0.0534347785,"repetition_step":0.0974859744,"discourse_representation":0.0024869442,"coherence_step_vs_step":0.0024709105,"perplexity_step":0.0055928958,"perplexity_chain":0.0248056132,"perplexity_step_max":0.0015833844,"grammar_step":0.8715339104,"grammar_step_max":0.799739778},{"ID":95,"faithfulness":0.8464630147,"informativeness_step":0.8013766945,"informativeness_chain":0.914782688,"faithfulness_ww":0.9495230141,"repetition_word":0.0314938927,"repetition_step":0.0581894815,"discourse_representation":0.0198219419,"coherence_step_vs_step":0.2508493662,"perplexity_step":0.0273128645,"perplexity_chain":0.0648855204,"perplexity_step_max":0.0238782114,"grammar_step":0.9719504515,"grammar_step_max":0.9313200116},{"ID":96,"faithfulness":0.7731379643,"informativeness_step":0.7343728812,"informativeness_chain":0.8351348713,"faithfulness_ww":0.9385514846,"repetition_word":0.0475649782,"repetition_step":0.1072855443,"discourse_representation":0.0155577064,"coherence_step_vs_step":0.4236779213,"perplexity_step":0.0096169417,"perplexity_chain":0.0283548134,"perplexity_step_max":0.0063985193,"grammar_step":0.891874671,"grammar_step_max":0.8285976052},{"ID":97,"faithfulness":0.8406052291,"informativeness_step":0.7908969758,"informativeness_chain":0.9059567451,"faithfulness_ww":0.9512029822,"repetition_word":0.0742714405,"repetition_step":0.0425037742,"discourse_representation":0.2801514864,"coherence_step_vs_step":0.9920162857,"perplexity_step":0.0051034172,"perplexity_chain":0.0362801698,"perplexity_step_max":0.0020614774,"grammar_step":0.9854377806,"grammar_step_max":0.9837802052},{"ID":98,"faithfulness":0.8035006076,"informativeness_step":0.76931708,"informativeness_chain":0.9227351546,"faithfulness_ww":0.9567402899,"repetition_word":0.0433443444,"repetition_step":0.2139020301,"discourse_representation":0.9934875541,"coherence_step_vs_step":0.9990864387,"perplexity_step":0.0090395117,"perplexity_chain":0.0138605388,"perplexity_step_max":0.0051584879,"grammar_step":0.922644347,"grammar_step_max":0.9000769258},{"ID":99,"faithfulness":0.870875448,"informativeness_step":0.8085690187,"informativeness_chain":0.8782288432,"faithfulness_ww":0.941012506,"repetition_word":0.0427746618,"repetition_step":0.0299121141,"discourse_representation":0.9045215324,"coherence_step_vs_step":0.9335746169,"perplexity_step":0.0208668375,"perplexity_chain":0.0738822416,"perplexity_step_max":0.0087042474,"grammar_step":0.9436589479,"grammar_step_max":0.9148436785},{"ID":100,"faithfulness":0.798288395,"informativeness_step":0.8116580586,"informativeness_chain":0.9389942288,"faithfulness_ww":0.9433654751,"repetition_word":0.0520192871,"repetition_step":0.0546939522,"discourse_representation":0.0005066395,"coherence_step_vs_step":0.0008171201,"perplexity_step":0.028694548,"perplexity_chain":0.0651880725,"perplexity_step_max":0.0242507807,"grammar_step":0.8533004125,"grammar_step_max":0.5756950378},{"ID":101,"faithfulness":0.8270358741,"informativeness_step":0.7685053175,"informativeness_chain":0.8566025645,"faithfulness_ww":0.9216905458,"repetition_word":1.0,"repetition_step":1.0,"discourse_representation":0.6649272442,"coherence_step_vs_step":0.9651282281,"perplexity_step":0.0264083842,"perplexity_chain":0.0264083842,"perplexity_step_max":0.0264083842,"grammar_step":0.9812198877,"grammar_step_max":0.9812198877},{"ID":102,"faithfulness":0.9288409948,"informativeness_step":0.8784075389,"informativeness_chain":0.9408786744,"faithfulness_ww":0.9587302665,"repetition_word":1.0,"repetition_step":1.0,"discourse_representation":0.1044852734,"coherence_step_vs_step":0.9812713489,"perplexity_step":0.0760280986,"perplexity_chain":0.0760280986,"perplexity_step_max":0.0760280986,"grammar_step":0.9415673614,"grammar_step_max":0.9415673614},{"ID":103,"faithfulness":0.9026246667,"informativeness_step":0.8648218662,"informativeness_chain":0.9356096387,"faithfulness_ww":0.9706359149,"repetition_word":1.0,"repetition_step":1.0,"discourse_representation":0.0137560964,"coherence_step_vs_step":0.9983148082,"perplexity_step":0.0332252018,"perplexity_chain":0.0332252018,"perplexity_step_max":0.0332252018,"grammar_step":0.9936788678,"grammar_step_max":0.9936788678},{"ID":104,"faithfulness":0.8187172674,"informativeness_step":0.8134068688,"informativeness_chain":0.896001488,"faithfulness_ww":0.9595736649,"repetition_word":0.0460632909,"repetition_step":0.0784324408,"discourse_representation":0.5722498894,"coherence_step_vs_step":0.6739146113,"perplexity_step":0.0111976679,"perplexity_chain":0.0474755505,"perplexity_step_max":0.0060508655,"grammar_step":0.8121851683,"grammar_step_max":0.5863112807},{"ID":105,"faithfulness":0.7555946037,"informativeness_step":0.7451139435,"informativeness_chain":0.9217399508,"faithfulness_ww":0.9435796408,"repetition_word":0.0474819988,"repetition_step":0.1004905105,"discourse_representation":0.996575498,"coherence_step_vs_step":0.999363262,"perplexity_step":0.0169512726,"perplexity_chain":0.0387199345,"perplexity_step_max":0.0083316244,"grammar_step":0.9850025177,"grammar_step_max":0.9797087312},{"ID":106,"faithfulness":0.8108759969,"informativeness_step":0.7966054231,"informativeness_chain":0.9327841103,"faithfulness_ww":0.95269159,"repetition_word":0.054565345,"repetition_step":0.101434052,"discourse_representation":0.9829903133,"coherence_step_vs_step":0.9975930401,"perplexity_step":0.0114189283,"perplexity_chain":0.0424190519,"perplexity_step_max":0.0025561195,"grammar_step":0.9743606846,"grammar_step_max":0.9524721503},{"ID":107,"faithfulness":0.8978875428,"informativeness_step":0.8095616139,"informativeness_chain":0.8850970268,"faithfulness_ww":0.9589308005,"repetition_word":0.0542645877,"repetition_step":0.122102201,"discourse_representation":0.8587703109,"coherence_step_vs_step":0.9907884561,"perplexity_step":0.0085852942,"perplexity_chain":0.0172201253,"perplexity_step_max":0.0082011053,"grammar_step":0.9146066308,"grammar_step_max":0.8374578953},{"ID":108,"faithfulness":0.8542539924,"informativeness_step":0.7998493388,"informativeness_chain":0.8841433525,"faithfulness_ww":0.9552634951,"repetition_word":0.0529157349,"repetition_step":0.0580481291,"discourse_representation":0.8309502304,"coherence_step_vs_step":0.9985429744,"perplexity_step":0.0453545101,"perplexity_chain":0.075909897,"perplexity_step_max":0.0431237852,"grammar_step":0.9660224915,"grammar_step_max":0.9455670118},{"ID":109,"faithfulness":0.7398855786,"informativeness_step":0.7183083971,"informativeness_chain":0.8744938448,"faithfulness_ww":0.9497796864,"repetition_word":0.0326919449,"repetition_step":0.0581812263,"discourse_representation":0.0096290708,"coherence_step_vs_step":0.99053308,"perplexity_step":0.0216630863,"perplexity_chain":0.0513429058,"perplexity_step_max":0.0055364484,"grammar_step":0.9888023933,"grammar_step_max":0.9865343571},{"ID":110,"faithfulness":0.9298967322,"informativeness_step":0.8287189777,"informativeness_chain":0.8940344751,"faithfulness_ww":0.9612886187,"repetition_word":0.0430841053,"repetition_step":0.0346514285,"discourse_representation":0.9954994088,"coherence_step_vs_step":0.9979153913,"perplexity_step":0.0136970222,"perplexity_chain":0.0432960352,"perplexity_step_max":0.008164245,"grammar_step":0.9377953013,"grammar_step_max":0.8312561512},{"ID":111,"faithfulness":0.8494573335,"informativeness_step":0.8276964804,"informativeness_chain":0.9366123229,"faithfulness_ww":0.9485987602,"repetition_word":0.0454618608,"repetition_step":0.0637742132,"discourse_representation":0.979047671,"coherence_step_vs_step":0.9958605864,"perplexity_step":0.0264142019,"perplexity_chain":0.1145227329,"perplexity_step_max":0.0077506972,"grammar_step":0.9672278563,"grammar_step_max":0.946993351},{"ID":112,"faithfulness":0.7666532397,"informativeness_step":0.7600175525,"informativeness_chain":0.9147807509,"faithfulness_ww":0.9556337118,"repetition_word":0.0346060903,"repetition_step":0.063874945,"discourse_representation":0.244669795,"coherence_step_vs_step":0.0405782461,"perplexity_step":0.0285699664,"perplexity_chain":0.0998204383,"perplexity_step_max":0.0221797962,"grammar_step":0.9843308528,"grammar_step_max":0.9756879807},{"ID":113,"faithfulness":0.8390765488,"informativeness_step":0.7978281811,"informativeness_chain":0.8849069029,"faithfulness_ww":0.9076813429,"repetition_word":1.0,"repetition_step":1.0,"discourse_representation":0.9754686039,"coherence_step_vs_step":0.9967963449,"perplexity_step":0.291443753,"perplexity_chain":0.291443753,"perplexity_step_max":0.291443753,"grammar_step":0.9882565141,"grammar_step_max":0.9882565141},{"ID":114,"faithfulness":0.8085142076,"informativeness_step":0.7761777975,"informativeness_chain":0.8783040643,"faithfulness_ww":0.9420351368,"repetition_word":1.0,"repetition_step":1.0,"discourse_representation":0.2162430286,"coherence_step_vs_step":0.9994554852,"perplexity_step":0.0016534512,"perplexity_chain":0.0016534512,"perplexity_step_max":0.0016534512,"grammar_step":0.1686504036,"grammar_step_max":0.1686504036},{"ID":115,"faithfulness":0.7869060487,"informativeness_step":0.7672819172,"informativeness_chain":0.8972082138,"faithfulness_ww":0.9602003409,"repetition_word":0.0829850719,"repetition_step":0.1827083081,"discourse_representation":0.8197722137,"coherence_step_vs_step":0.2044845223,"perplexity_step":0.0033811585,"perplexity_chain":0.0181465907,"perplexity_step_max":0.0016581696,"grammar_step":0.9823299348,"grammar_step_max":0.9737833738},{"ID":116,"faithfulness":0.6822272708,"informativeness_step":0.7263752729,"informativeness_chain":0.9154618233,"faithfulness_ww":0.9179856503,"repetition_word":0.011131564,"repetition_step":0.0413493663,"discourse_representation":0.1668660045,"coherence_step_vs_step":0.0023328066,"perplexity_step":0.0025362232,"perplexity_chain":0.2153827672,"perplexity_step_max":0.0013517301,"grammar_step":0.6290820777,"grammar_step_max":0.4568361342},{"ID":117,"faithfulness":0.8715215623,"informativeness_step":0.8185181439,"informativeness_chain":0.9556315839,"faithfulness_ww":0.9443903026,"repetition_word":0.0546128535,"repetition_step":0.064965263,"discourse_representation":0.9860727023,"coherence_step_vs_step":0.9973098971,"perplexity_step":0.0079507617,"perplexity_chain":0.0465078211,"perplexity_step_max":0.0027743914,"grammar_step":0.9766464233,"grammar_step_max":0.9613486528},{"ID":118,"faithfulness":0.6970899217,"informativeness_step":0.7317844834,"informativeness_chain":0.9023075104,"faithfulness_ww":0.9548450451,"repetition_word":0.0259363651,"repetition_step":0.0421404988,"discourse_representation":0.0499371886,"coherence_step_vs_step":0.0032492876,"perplexity_step":0.0050218027,"perplexity_chain":0.0664893096,"perplexity_step_max":0.0007327936,"grammar_step":0.9678540647,"grammar_step_max":0.9469999671},{"ID":119,"faithfulness":0.8781757951,"informativeness_step":0.8298748966,"informativeness_chain":0.9251534194,"faithfulness_ww":0.9695889329,"repetition_word":0.0434672562,"repetition_step":0.0852321982,"discourse_representation":0.0751866698,"coherence_step_vs_step":0.9956377582,"perplexity_step":0.0061046195,"perplexity_chain":0.0229165138,"perplexity_step_max":0.0023723172,"grammar_step":0.9804020325,"grammar_step_max":0.9663662314},{"ID":120,"faithfulness":0.8264483586,"informativeness_step":0.7811518971,"informativeness_chain":0.9070875645,"faithfulness_ww":0.9684049708,"repetition_word":0.04195351,"repetition_step":0.1382111758,"discourse_representation":0.0294023156,"coherence_step_vs_step":0.9907029029,"perplexity_step":0.0106432916,"perplexity_chain":0.0245549527,"perplexity_step_max":0.0035907025,"grammar_step":0.9783403873,"grammar_step_max":0.9413480759},{"ID":121,"faithfulness":0.7399420713,"informativeness_step":0.7496490257,"informativeness_chain":0.8885779828,"faithfulness_ww":0.9425598694,"repetition_word":0.0477796445,"repetition_step":0.1852759644,"discourse_representation":0.0016545057,"coherence_step_vs_step":0.9942328441,"perplexity_step":0.0131092164,"perplexity_chain":0.0242667727,"perplexity_step_max":0.0098902375,"grammar_step":0.9774468939,"grammar_step_max":0.9557726383},{"ID":122,"faithfulness":0.889673382,"informativeness_step":0.8156695902,"informativeness_chain":0.859409906,"faithfulness_ww":0.9623593452,"repetition_word":0.0486822493,"repetition_step":0.2183648199,"discourse_representation":0.1477892399,"coherence_step_vs_step":0.9971912801,"perplexity_step":0.0109250161,"perplexity_chain":0.0261140376,"perplexity_step_max":0.0029083706,"grammar_step":0.703611955,"grammar_step_max":0.4294829071},{"ID":123,"faithfulness":0.8722698152,"informativeness_step":0.8694021379,"informativeness_chain":0.9609726071,"faithfulness_ww":0.9743368694,"repetition_word":0.0387380658,"repetition_step":0.0615470856,"discourse_representation":0.8083083183,"coherence_step_vs_step":0.9518024251,"perplexity_step":0.0205904398,"perplexity_chain":0.0592187758,"perplexity_step_max":0.0041107583,"grammar_step":0.9112478733,"grammar_step_max":0.8020395637},{"ID":124,"faithfulness":0.9024153352,"informativeness_step":0.8825352341,"informativeness_chain":0.9549901932,"faithfulness_ww":0.9582952662,"repetition_word":0.0400484204,"repetition_step":0.0572814941,"discourse_representation":0.9748152383,"coherence_step_vs_step":0.9923599861,"perplexity_step":0.0128316405,"perplexity_chain":0.0602287564,"perplexity_step_max":0.0036782873,"grammar_step":0.9888277948,"grammar_step_max":0.9874558449},{"ID":125,"faithfulness":0.7534163147,"informativeness_step":0.7408494949,"informativeness_chain":0.884354502,"faithfulness_ww":0.9534299572,"repetition_word":0.0360252293,"repetition_step":0.1722974703,"discourse_representation":0.0014818311,"coherence_step_vs_step":0.7807719707,"perplexity_step":0.0132417528,"perplexity_chain":0.0399948958,"perplexity_step_max":0.007927545,"grammar_step":0.8980367482,"grammar_step_max":0.6974916458},{"ID":126,"faithfulness":0.8565830886,"informativeness_step":0.8122329246,"informativeness_chain":0.9219498038,"faithfulness_ww":0.9624044549,"repetition_word":1.0,"repetition_step":1.0,"discourse_representation":0.8416768909,"coherence_step_vs_step":0.9948794073,"perplexity_step":0.0231068142,"perplexity_chain":0.0231068142,"perplexity_step_max":0.0231068142,"grammar_step":0.9931693077,"grammar_step_max":0.9931693077},{"ID":127,"faithfulness":0.734772707,"informativeness_step":0.7073654889,"informativeness_chain":0.8971517086,"faithfulness_ww":0.9419112397,"repetition_word":0.0525315087,"repetition_step":0.1514913589,"discourse_representation":0.0029441118,"coherence_step_vs_step":0.8202881366,"perplexity_step":0.0219092113,"perplexity_chain":0.0466732642,"perplexity_step_max":0.0159514959,"grammar_step":0.9639166594,"grammar_step_max":0.9165124893},{"ID":128,"faithfulness":0.7996002436,"informativeness_step":0.7554800222,"informativeness_chain":0.935222134,"faithfulness_ww":0.9513756843,"repetition_word":0.0558481233,"repetition_step":0.138500385,"discourse_representation":0.0665634871,"coherence_step_vs_step":0.9983429338,"perplexity_step":0.0078486677,"perplexity_chain":0.0162166624,"perplexity_step_max":0.0066901615,"grammar_step":0.7783588469,"grammar_step_max":0.6037297249},{"ID":129,"faithfulness":0.8839508891,"informativeness_step":0.7951264344,"informativeness_chain":0.936102435,"faithfulness_ww":0.9525727229,"repetition_word":1.0,"repetition_step":1.0,"discourse_representation":0.0391452312,"coherence_step_vs_step":0.9985913188,"perplexity_step":0.0109809236,"perplexity_chain":0.0109809236,"perplexity_step_max":0.0109809236,"grammar_step":0.9768486023,"grammar_step_max":0.9768486023},{"ID":130,"faithfulness":0.8011683623,"informativeness_step":0.7940394667,"informativeness_chain":0.9116897285,"faithfulness_ww":0.9419063087,"repetition_word":0.0456240164,"repetition_step":0.0912387222,"discourse_representation":0.6311729252,"coherence_step_vs_step":0.846171543,"perplexity_step":0.0284726339,"perplexity_chain":0.070030949,"perplexity_step_max":0.0207521806,"grammar_step":0.9666489959,"grammar_step_max":0.9332820773},{"ID":131,"faithfulness":0.6766582206,"informativeness_step":0.6717937037,"informativeness_chain":0.8815732598,"faithfulness_ww":0.9354784187,"repetition_word":0.0670193786,"repetition_step":0.1377380937,"discourse_representation":0.0021162629,"coherence_step_vs_step":0.9987788728,"perplexity_step":0.0157014475,"perplexity_chain":0.0267547449,"perplexity_step_max":0.0152614533,"grammar_step":0.9451452494,"grammar_step_max":0.9379186034},{"ID":132,"faithfulness":0.8622417549,"informativeness_step":0.8134287839,"informativeness_chain":0.9068369865,"faithfulness_ww":0.9453167066,"repetition_word":0.0436429907,"repetition_step":0.0864289701,"discourse_representation":0.9975134721,"coherence_step_vs_step":0.9975637798,"perplexity_step":0.026903626,"perplexity_chain":0.0521172073,"perplexity_step_max":0.0194006888,"grammar_step":0.976933519,"grammar_step_max":0.9467878938},{"ID":133,"faithfulness":0.7468817756,"informativeness_step":0.6869739964,"informativeness_chain":0.8888131082,"faithfulness_ww":0.9654832292,"repetition_word":0.0651103428,"repetition_step":0.1759208366,"discourse_representation":0.0138770342,"coherence_step_vs_step":0.998729306,"perplexity_step":0.0086395972,"perplexity_chain":0.0254718704,"perplexity_step_max":0.0037476956,"grammar_step":0.8002598286,"grammar_step_max":0.6324246526},{"ID":134,"faithfulness":0.8347620219,"informativeness_step":0.7800958094,"informativeness_chain":0.9007671624,"faithfulness_ww":0.9543263158,"repetition_word":0.0491813584,"repetition_step":0.1338093132,"discourse_representation":0.0019416213,"coherence_step_vs_step":0.9748736732,"perplexity_step":0.0090309986,"perplexity_chain":0.0234598402,"perplexity_step_max":0.0040831095,"grammar_step":0.8873383105,"grammar_step_max":0.8274136186},{"ID":135,"faithfulness":0.7985722274,"informativeness_step":0.785358306,"informativeness_chain":0.9417078197,"faithfulness_ww":0.9465317503,"repetition_word":0.0610380545,"repetition_step":0.243565551,"discourse_representation":0.8309024274,"coherence_step_vs_step":0.9981285268,"perplexity_step":0.0195388797,"perplexity_chain":0.0261202769,"perplexity_step_max":0.01755972,"grammar_step":0.9855558574,"grammar_step_max":0.9855029583}]